enigmacifra/__init__.py
enigmacifra/cliengine.py
enigmacifra/defaultRotor.py
enigmacifra/engine.py
enigmacifra/mshuffle.py
enigmacifra-0.2.0.dist-info/LICENSE
enigmacifra-0.2.0.dist-info/METADATA
enigmacifra-0.2.0.dist-info/WHEEL
enigmacifra-0.2.0.dist-info/entry_points.txt
enigmacifra-0.2.0.dist-info/top_level.txt
enigmacifra-0.2.0.dist-info/RECORD
