Metadata-Version: 2.1
Name: enigmacifra
Version: 0.2.0
Summary: PIN encrypted enigma machine cipher texts
Home-page: https://github.com/1darshanpatil/enigmacipher
Author: Darshan P.
Author-email: drshnp@outlook.com
License: MIT
Project-URL: Documentation, https://github.com/1darshanpatil/enigmacipher#readme
Project-URL: Source, https://github.com/1darshanpatil/enigmacipher
Project-URL: Tracker, https://github.com/1darshanpatil/enigmacipher/issues
Keywords: enigma,cipher,encryption
Classifier: Development Status :: 4 - Beta
Classifier: Programming Language :: Python :: 3
Classifier: License :: OSI Approved :: MIT License
Classifier: Operating System :: OS Independent
Requires-Python: >=3.6
License-File: LICENSE
